pyannote/core/__init__.py
pyannote/core/annotation.py
pyannote/core/feature.py
pyannote/core/notebook.py
pyannote/core/segment.py
pyannote/core/timeline.py
pyannote/core/utils/__init__.py
pyannote/core/utils/cluster.py
pyannote/core/utils/distance.py
pyannote/core/utils/generators.py
pyannote/core/utils/helper.py
pyannote/core/utils/hierarchy.py
pyannote/core/utils/numpy.py
pyannote/core/utils/random.py
pyannote/core/utils/types.py
pyannote_core-6.0.0.dist-info/METADATA
pyannote_core-6.0.0.dist-info/WHEEL
pyannote_core-6.0.0.dist-info/licenses/LICENSE
pyannote_core-6.0.0.dist-info/RECORD
