Metadata-Version: 2.4
Name: pyannote-core
Version: 6.0.0
Summary: Advanced data structures for handling temporal segments with attached labels
Author-email: Hervé BREDIN <herve@pyannote.ai>
License-File: LICENSE
Requires-Python: >=3.10
Requires-Dist: numpy>=2.0
Requires-Dist: pandas>=2.2.3
Requires-Dist: sortedcontainers>=2.4.0
Provides-Extra: doc
Requires-Dist: ipython>=8.32.0; extra == 'doc'
Requires-Dist: matplotlib>=3.10.0; extra == 'doc'
Requires-Dist: sphinx-rtd-theme>=3.0.2; extra == 'doc'
Requires-Dist: sphinx>=8.1.3; extra == 'doc'
Provides-Extra: notebook
Requires-Dist: ipython>=8.31.0; extra == 'notebook'
Requires-Dist: matplotlib>=3.10.0; extra == 'notebook'
Provides-Extra: test
Requires-Dist: matplotlib>=3.10.0; extra == 'test'
Requires-Dist: pytest>=8.3.4; extra == 'test'
